rich_codex/__init__.py
rich_codex/__main__.py
rich_codex/cli.py
rich_codex/codex_search.py
rich_codex/config-schema.yml
rich_codex/rich_img.py
rich_codex/utils.py
rich_codex-1.2.11.dist-info/licenses/LICENSE
rich_codex-1.2.11.dist-info/METADATA
rich_codex-1.2.11.dist-info/WHEEL
rich_codex-1.2.11.dist-info/entry_points.txt
rich_codex-1.2.11.dist-info/top_level.txt
rich_codex-1.2.11.dist-info/RECORD
