Metadata-Version: 2.4
Name: rich-codex
Version: 1.2.11
Summary: Generate rich images for the GitHub Action 'rich-codex'
Author-email: Phil Ewels <phil@ewels.co.uk>
Maintainer-email: Phil Ewels <phil@ewels.co.uk>
License-Expression: MIT
Project-URL: Documentation, https://github.com/ewels/rich-codex
Project-URL: Source Code, https://github.com/ewels/rich-codex
Project-URL: Issue Tracker, https://github.com/ewels/rich-codex/issues
Classifier: Development Status :: 3 - Alpha
Classifier: Intended Audience :: Developers
Classifier: Operating System :: OS Independent
Classifier: Programming Language :: Python
Classifier: Programming Language :: Python :: 3 :: Only
Classifier: Programming Language :: Python :: 3.7
Classifier: Programming Language :: Python :: 3.8
Classifier: Programming Language :: Python :: 3.9
Classifier: Programming Language :: Python :: 3.10
Classifier: Programming Language :: Python :: 3.11
Classifier: Programming Language :: Python :: 3.12
Requires-Python: >=3.7
License-File: LICENSE
Requires-Dist: rich>=12.4.3
Requires-Dist: rich-click>=1.5
Requires-Dist: importlib-metadata; python_version < "3.8"
Requires-Dist: pyyaml
Requires-Dist: levenshtein>=0.18.1
Requires-Dist: jsonschema
Requires-Dist: GitPython
Provides-Extra: dev
Requires-Dist: pre-commit; extra == "dev"
Provides-Extra: cairo
Requires-Dist: CairoSVG>=2.5.2; extra == "cairo"
Dynamic: license-file
